conscience/__init__.py
conscience/common.py
conscience/config.py
conscience/formatters.py
conscience/lib/__init__.py
conscience/lib/grid.py
conscience/lib/identify.py
conscience/lib/images.py
conscience/lib/mocking.py
conscience/lobes/__init__.py
conscience/lobes/after.py
conscience/lobes/design.py
conscience/lobes/keyboard.py
conscience/lobes/lobe.py
conscience/lobes/menu.py
conscience/lobes/messagebox.py
conscience/lobes/tk_lifecycle.py
conscience/main.py
conscience/parsers.py
conscience/score.py
conscience/suite.py
conscience-0.1.0.dist-info/METADATA
conscience-0.1.0.dist-info/WHEEL
conscience-0.1.0.dist-info/RECORD
